pycounts_bzrudski/__init__.py
pycounts_bzrudski/data/__init__.py
pycounts_bzrudski/data/flatland.txt
pycounts_bzrudski/datasets.py
pycounts_bzrudski/plotting.py
pycounts_bzrudski/pycounts_bzrudski.py
pycounts_bzrudski-1.0.0.dist-info/LICENSE
pycounts_bzrudski-1.0.0.dist-info/METADATA
pycounts_bzrudski-1.0.0.dist-info/WHEEL
pycounts_bzrudski-1.0.0.dist-info/RECORD
