Metadata-Version: 2.3
Name: pycounts_bzrudski
Version: 1.0.0
Summary: Calculate word counts in a text file!
License: MIT
Author: bzrudski
Requires-Python: >=3.9
Classifier: License :: OSI Approved :: MIT License
Classifier: Programming Language :: Python :: 3
Classifier: Programming Language :: Python :: 3.9
Classifier: Programming Language :: Python :: 3.10
Classifier: Programming Language :: Python :: 3.11
Classifier: Programming Language :: Python :: 3.12
Classifier: Programming Language :: Python :: 3.13
Requires-Dist: matplotlib (>=3.9.4)
Project-URL: Documentation, https://pycounts-bzrudski.readthedocs.io/en/latest/index.html
Project-URL: Homepage, https://github.com/bzrudski/pycounts_bzrudski
Project-URL: Repository, https://github.com/bzrudski/pycounts_bzrudski
